asciinema_automation/__init__.py
asciinema_automation/__main__.py
asciinema_automation/cli.py
asciinema_automation/instruction.py
asciinema_automation/parse.py
asciinema_automation/script.py
asciinema_automation-0.2.2.dist-info/LICENSE
asciinema_automation-0.2.2.dist-info/METADATA
asciinema_automation-0.2.2.dist-info/WHEEL
asciinema_automation-0.2.2.dist-info/entry_points.txt
asciinema_automation-0.2.2.dist-info/top_level.txt
asciinema_automation-0.2.2.dist-info/RECORD
