Metadata-Version: 2.1
Name: asciinema-automation
Version: 0.2.2
Summary: CLI utility to automate asciinema
Author-email: Pierre Marchand <test@test.com>
License: MIT License
Project-URL: Homepage, https://github.com/PierreMarchand20/asciinema_automation
Project-URL: Bug Tracker, https://github.com/PierreMarchand20/asciinema_automation/issues
Keywords: asciinema
Classifier: Programming Language :: Python :: 3
Classifier: License :: OSI Approved :: MIT License
Classifier: Operating System :: MacOS
Classifier: Operating System :: Unix
Requires-Python: >=3.7
License-File: LICENSE
Requires-Dist: pexpect >=4.8.0
Requires-Dist: asciinema >=2.2.0
Provides-Extra: dev
Requires-Dist: ruff ; extra == 'dev'
Requires-Dist: pytest ; extra == 'dev'
Requires-Dist: mypy ; extra == 'dev'
Requires-Dist: types-pexpect ; extra == 'dev'
